The Architects-ProjectStep2/verilog/mult_4b/mult_4b.v
module mult_4b(x, y, out);

  output [3:0] out;
  input [3:0] x, y;

  wire x, y, out;

  assign out = x * y;

endmodule

The Architects-ProjectStep2/verilog/mult_4b/mult_4b_test.v
module mult_4b_test;

  /* Make a regular pulsing clock. */
  reg clk = 0;
  always #10 clk = !clk;

  reg [3:0] x = 0;
  reg [3:0] y = 0;
  reg Cin = 1;
  initial begin
     # 10 x = 4'b1000;
     # 10 y = 4'b1001;
     # 10 Cin = 0;
     # 10 x = 4'b1101;
     # 10 y = 4'b0110;
     # 10 Cin = 1;
     # 10 x = 4'b1000;
     # 10 y = 4'b1001;
     # 10 $finish;
  end

  wire [7:0] out;
  wire Cout;
  mult_4b a0 (x, y, out, Cin, Cout);

  initial begin
    $dumpfile("mult_4b.vcd");
     $dumpvars(0,clk);
     $dumpvars(1,x);
     $dumpvars(2,y);
     $dumpvars(3,out);
    $dumpvars (4, Cout);
    $dumpvars (5, Cin);
  end

  initial
     $monitor("At time %t, x(%b) * y(%b) *Cin(%b) = out(%b) with Cout(%b)",
              $time, x, y, out, Cout, Cin);
endmodule // test

The Architects-ProjectStepFinal/verilog/mult_4b/mult_4b.vcd
$date
	Tue Oct 31 17:13:14 2023
$end
$version
	Icarus Verilog
$end
$timescale
	1s
$end
$scope module mult_4b_test $end
$var reg 1 ! clk $end
$upscope $end
$scope module mult_4b_test $end
$var reg 4 " x [3:0] $end
$upscope $end
$scope module mult_4b_test $end
$var reg 4 # y [3:0] $end
$upscope $end
$scope module mult_4b_test $end
$var wire 8 $ out [7:0] $end
$upscope $end
$scope module mult_4b_test $end
$var wire 1 % Cout $end
$upscope $end
$scope module mult_4b_test $end
$var reg 1 & Cin $end
$upscope $end
$enddefinitions $end
$comment Show the parameter values. $end
$dumpall
$end
#0
$dumpvars
1&
0%
b0 $
b0 #
b0 "
0!
$end
#10
b1000 "
1!
#20
b1001000 $
b1001 #
0!
#30
b0 $
0&
1!
#40
b1101 "
0!
#50
b110 #
1!
#60
b1001110 $
1&
0!
#70
b110000 $
b1000 "
1!
#80
b1001000 $
b1001 #
0!
