step_1/nand_1b/nand_1b.v
module nand_1b(x, y, ci, out);

  output o, out;
  input x, y, ci;

  wire x, y, ci, out;

  assign out = ~((x & y) | (x & ci) | (y & ci));

endmodule

step_1/nand_1b/nand_1b_test.v
module nand_1b_test;

  /* Make a regular pulsing clock. */
  reg clk = 0;
  always #5 clk = !clk;

  reg x = 0;
  reg y = 0;
  reg ci = 0;
  initial begin
     # 10 x = 1;
     # 10 y = 1;
     # 10 ci = 1;
     # 10 y = 0;
     # 10 x = 0;
     # 10 y = 1;
     # 10 ci = 0;
     # 10 $finish;
  end

  wire o;
  wire out;
  nand_1b a0 (x, y, ci, out);
  
  initial begin
     $dumpfile("nand_1b.vcd");
     $dumpvars(0,clk);
     $dumpvars(1,x);
     $dumpvars(2,y);
     $dumpvars(3,ci);
     $dumpvars(5,out);
  end
  
  initial
     $monitor("At time %t, x(%b) + y(%b) + ci(%b) = out(%b)",
              $time, x, y, ci, out);
endmodule // test

step_1/nand_1b/nand_1b.vcd
$date
	Sun Sep 17 19:04:20 2023
$end
$version
	Icarus Verilog
$end
$timescale
	1s
$end
$scope module nand_1b_test $end
$var reg 1 ! clk $end
$upscope $end
$scope module nand_1b_test $end
$var reg 1 " x $end
$upscope $end
$scope module nand_1b_test $end
$var reg 1 # y $end
$upscope $end
$scope module nand_1b_test $end
$var reg 1 $ ci $end
$upscope $end
$scope module nand_1b_test $end
$var wire 1 % out $end
$upscope $end
$enddefinitions $end
$comment Show the parameter values. $end
$dumpall
$end
#0
$dumpvars
1%
0$
0#
0"
0!
$end
#5
1!
#10
0!
1"
#15
1!
#20
0%
0!
1#
#25
1!
#30
0!
1$
#35
1!
#40
0!
0#
#45
1!
#50
1%
0!
0"
#55
1!
#60
0%
0!
1#
#65
1!
#70
1%
0!
0$
