The Architects-ProjectStepFinal/latex/verilog/add_4b/add_4b.v
module add_4b(x, y, out, Cin, Cout);

  output [3:0] out;
  output Cout;
  input [3:0] x, y;
  input Cin;

  wire x, y, out;

  assign {Cout, out} = x + y + Cin;
  

endmodule

The Architects-ProjectStepFinal/verilog/add_4b/add_4b_test.v
module add_4b_test;

  /* Make a regular pulsing clock. */
  reg clk = 0;
  always #10 clk = !clk;

  reg [3:0] x = 0;
  reg [3:0] y = 0;
  reg Cin = 0;
  initial begin
     # 10 x = 4'b1000;
     # 10 y = 4'b1001;
     # 10 Cin = 1;
     # 10 x = 4'b1101;
     # 10 y = 4'b0110;
     # 10 Cin = 0;
     # 10 x = 4'b1000;
     # 10 y = 4'b1001;
     # 10 $finish;
  end

  wire [3:0] out;
  wire Cout;
  add_4b a0 (x, y, out, Cin, Cout);
  
  initial begin
     $dumpfile("add_4b.vcd");
     $dumpvars(0,clk);
     $dumpvars(1,x);
     $dumpvars(2,y);
     $dumpvars(3,out);
    $dumpvars (4, Cout);
    $dumpvars (5, Cin);
  end
  
  initial
     $monitor("At time %t, x(%b) + y(%b) + Cin(%b)= out(%b) with Cout(%b)",
              $time, x, y, Cin, out, Cout);
endmodule // test

The Architects-ProjectStepFinal/add_4b/add_4b.vcd
$date
	Tue Oct 31 17:06:16 2023
$end
$version
	Icarus Verilog
$end
$timescale
	1s
$end
$scope module add_4b_test $end
$var reg 1 ! clk $end
$upscope $end
$scope module add_4b_test $end
$var reg 4 " x [3:0] $end
$upscope $end
$scope module add_4b_test $end
$var reg 4 # y [3:0] $end
$upscope $end
$scope module add_4b_test $end
$var wire 4 $ out [3:0] $end
$upscope $end
$scope module add_4b_test $end
$var wire 1 % Cout $end
$upscope $end
$scope module add_4b_test $end
$var reg 1 & Cin $end
$upscope $end
$enddefinitions $end
$comment Show the parameter values. $end
$dumpall
$end
#0
$dumpvars
0&
0%
b0 $
b0 #
b0 "
0!
$end
#10
b1000 $
b1000 "
1!
#20
b1 $
1%
b1001 #
0!
#30
b10 $
1&
1!
#40
b111 $
b1101 "
0!
#50
b100 $
b110 #
1!
#60
b11 $
0&
0!
#70
b1110 $
0%
b1000 "
1!
#80
b1 $
1%
b1001 #
0!
