The Architects-ProjectStep2/verilog/mult_4b/mult_4b.v
module mult_4b(x, y, out, Cin, Cout);

  output [7:0] out;
  output Cout;
  input [3:0] x, y;
  input Cin;

  wire x, y, out;

  assign {Cout, out} = (x * y) * Cin;
 

endmodule

The Architects-ProjectStepFinal/verilog/sub_4b/sub_4b.v
module sub_4b(x, y, out, Cin, Cout);

  output [3:0] out;
  output Cout;
  input [3:0] x, y;
  input Cin;

  wire x, y, out;

  assign {Cout, out} = x - y - Cin;

endmodule

The Architects-ProjectStepFinal/latex/verilog/add_4b/add_4b.v
module add_4b(x, y, out, Cin, Cout);

  output [3:0] out;
  output Cout;
  input [3:0] x, y;
  input Cin;

  wire x, y, out;

  assign {Cout, out} = x + y + Cin;
  

endmodule

The Architects-ProjectStepFinal/latex/verilog/not_4b/not_4b.v
module not_4b(x, out);

  output [3:0] out, o;
  input [3:0] x;

  wire x, out;

  assign out = ~x;

endmodule

The Architects-ProjectStepFinal/verilog/xnor_4b/xnor_4b.v
module xnor_4b(x, y, out);

  output [3:0] out;
  input [3:0] x, y;

  wire x, y, out;

  assign out = ~(x ^ y);

endmodule

The Architects-ProjectStepFinal/latex/verilog/xor_4b/xor_4b.v
module xor_4b(x, y, out);

  output [3:0] out;
  input [3:0] x, y;

  wire x, y, out;

  assign out = x ^ y;

endmodule

The Architects-ProjectStepFinal/nor_4b/nor_4b.v
module nor_4b(x, y, out);

  output [3:0] out;
  input [3:0] x, y;

  wire x, y, out;

  assign out = ~(x | y);

endmodule

The Architects-ProjectStepFinal/verilog/or_4b/or_4b.v
module or_4b(x, y, out);

  output [3:0] out;
  input [3:0] x, y;

  wire x, y, out;

  assign out = x | y;

endmodule

The Architects-ProjectStepFinal/latex/verilog/nand_4b/nand_4b.v
module nand_4b(x, y, out);

  output [3:0] out;
  input [3:0] x, y;

  wire x, y, out;

  assign out = ~(x & y);

endmodule

The Architects-ProjectStepFinal/verilog/and_4b/and_4b.v
module and_4b(x, y, out);

  output [3:0] out;
  input [3:0] x, y;

  wire x, y, out;

  assign out = x & y;

endmodule

The Architects-ProjectStepFinal/control/control_test.v
module control_test;

  /* Make a regular pulsing clock. */
  reg clk = 0;
  always #10 clk = !clk;

  reg [3:0] x = 0;
  reg [3:0] y = 0;
  reg [3:0] operation = 0;
  reg [3:0] Result = 0;
  reg CinResult = 0;

  initial begin
     x = 4'b1101;
     y = 4'b1110;
     CinResult = 1;
     operation = 4'b0000;
     #10;
     x = 4'b1000;
     y = 4'b1000;
     CinResult = 0;
     operation = 4'b0001;
     #10;
     x = 4'b1010;
     y = 4'b1001;
     CinResult = 1;
     operation = 4'b0010;
     #10;
     x = 4'b1101;
     y = 4'b1110;
     CinResult = 1;
     operation = 4'b0011;
     #10;
     x = 4'b1101;
     y = 4'b1110;
     CinResult = 1;
     operation = 4'b0100;
     #10;
     x = 4'b1101;
     y = 4'b1110;
     CinResult = 1;
     operation = 4'b0101;
     #10;
     x = 4'b1101;
     y = 4'b1110;
     CinResult = 1;
     operation = 4'b0110;
     #10;
     x = 4'b1101;
     y = 4'b1110;
     CinResult = 1;
     operation = 4'b0111;
     #10;
     x = 4'b1101;
     y = 4'b1110;
     CinResult = 1;
     operation = 4'b1000;
     #10;
     x = 4'b1101;
     y = 4'b1110;
     CinResult = 1;
     operation = 4'b1001;
     #10;
     x = 4'b1101;
     y = 4'b1110;
     CinResult = 1;
     operation = 4'b1010;
     #10;
     $finish;
  end

  wire [3:0] AndResult, NandResult, OrResult, NorResult, XorResult, XnorResult, NotResult, ShiftResult, AddResult, SubResult;
  wire [7:0] MultResult;
  wire CoutResult;
  
  //instantiations
  and_4b and4(.x(x), .y(y), .out(AndResult));
  nand_4b nand4(.x(x), .y(y), .out(NandResult));
  or_4b or4(.x(x), .y(y), .out(OrResult));
  nor_4b nor4(.x(x), .y(y), .out(NorResult));
  xor_4b xor4(.x(x), .y(y), .out(XorResult));
  xnor_4b xnor4(.x(x), .y(y), .out(XnorResult));
  not_4b not4(.x(x), .out(NotResult));
  //shift_4b shift4(.x(x), .y(y), .out(ShiftResult));
  add_4b add4(.x(x), .y(y), .out(AddResult), .Cin(CinResult), .Cout(CoutResult));
  sub_4b sub4(.x(x), .y(y), .out(SubResult), .Cin(CinResult), .Cout(CoutResult));
  mult_4b mult4(.x(x), .y(y), .out(MultResult), .Cin(CinResult), .Cout(CoutResult));


//switch case
always @* begin
   case (operation)
      4'b0000: Result = AndResult;
      4'b0001: Result = NandResult;
      4'b0010: Result = OrResult;
      4'b0011: Result = NorResult;
      4'b0100: Result = XorResult;
      4'b0101: Result = XnorResult;
      4'b0110: Result = NotResult;
      4'b0111: Result = ShiftResult;
      4'b1000: Result = AddResult;
      4'b1001: Result = SubResult;
      4'b1010: Result = MultResult;
   endcase
end

  initial begin
     $dumpfile("control.vcd");
     $dumpvars(0,clk);
     $dumpvars(1,x);
     $dumpvars(2,y);
     $dumpvars (3, CoutResult);
     $dumpvars (4, CinResult);
     $dumpvars (5, Result);
  end
  
  initial
      $monitor("At time %t, x(%b) and y(%b) with CinResult(%b)= Result(%b) with CoutResult(%b)",
      $time, x, y, CinResult, Result, CoutResult);
endmodule

The Architects-ProjectStepFinal/control.vcd
$date
	Wed Nov 29 17:20:58 2023
$end
$version
	Icarus Verilog
$end
$timescale
	1s
$end
$scope module control_test $end
$var reg 1 ! clk $end
$upscope $end
$scope module control_test $end
$var reg 4 " x [3:0] $end
$upscope $end
$scope module control_test $end
$var reg 4 # y [3:0] $end
$upscope $end
$scope module control_test $end
$var wire 1 $ CoutResult $end
$upscope $end
$scope module control_test $end
$var reg 1 % CinResult $end
$upscope $end
$scope module control_test $end
$var reg 4 & Result [3:0] $end
$upscope $end
$enddefinitions $end
$comment Show the parameter values. $end
$dumpall
$end
#0
$dumpvars
b1100 &
1%
x$
b1110 #
b1101 "
0!
$end
#10
b111 &
0%
b1000 #
b1000 "
1!
#20
b1011 &
1%
b1001 #
b1010 "
0!
#30
b0 &
b1110 #
b1101 "
1!
#40
b11 &
0!
#50
b1100 &
1!
#60
b10 &
0!
#70
bz &
1!
#80
b1100 &
0!
#90
b1110 &
1!
#100
b110 &
0!
