The Architects-ProjectStep2/verilog/mult_4b/mult_4b.v
module mult_4b(x, y, out, Cin, Cout);

  output [7:0] out;
  output Cout;
  input [3:0] x, y;
  input Cin;

  wire x, y, out;

  assign {Cout, out} = (x * y) * Cin;
 

endmodule

The Architects-ProjectStepFinal/verilog/sub_4b/sub_4b.v
module sub_4b(x, y, out, Cin, Cout);

  output [3:0] out;
  output Cout;
  input [3:0] x, y;
  input Cin;

  wire x, y, out;

  assign {Cout, out} = x - y - Cin;

endmodule

The Architects-ProjectStepFinal/latex/verilog/add_4b/add_4b.v
module add_4b(x, y, out, Cin, Cout);

  output [3:0] out;
  output Cout;
  input [3:0] x, y;
  input Cin;

  wire x, y, out;

  assign {Cout, out} = x + y + Cin;
  

endmodule

The Architects-ProjectStepFinal/verilog/shift_4b/shift_4b.v
module shift_4b(x, y);

  output [3:0] xOut, yOut;
  input [3:0] x, y;

  wire [3:0] x, y, xOut, yOut;

  assign xOut = x;
  assign yOut = y;

endmodule

The Architects-ProjectStepFinal/latex/verilog/not_4b/not_4b.v
module not_4b(x, out);

  output [3:0] out, o;
  input [3:0] x;

  wire x, out;

  assign out = ~x;

endmodule

The Architects-ProjectStepFinal/verilog/xnor_4b/xnor_4b.v
module xnor_4b(x, y, out);

  output [3:0] out;
  input [3:0] x, y;

  wire x, y, out;

  assign out = ~(x ^ y);

endmodule

The Architects-ProjectStepFinal/latex/verilog/xor_4b/xor_4b.v
module xor_4b(x, y, out);

  output [3:0] out;
  input [3:0] x, y;

  wire x, y, out;

  assign out = x ^ y;

endmodule

The Architects-ProjectStepFinal/nor_4b/nor_4b.v
module nor_4b(x, y, out);

  output [3:0] out;
  input [3:0] x, y;

  wire x, y, out;

  assign out = ~(x | y);

endmodule

The Architects-ProjectStepFinal/verilog/or_4b/or_4b.v
module or_4b(x, y, out);

  output [3:0] out;
  input [3:0] x, y;

  wire x, y, out;

  assign out = x | y;

endmodule

The Architects-ProjectStepFinal/latex/verilog/nand_4b/nand_4b.v
module nand_4b(x, y, out);

  output [3:0] out;
  input [3:0] x, y;

  wire x, y, out;

  assign out = ~(x & y);

endmodule

The Architects-ProjectStepFinal/verilog/and_4b/and_4b.v
module and_4b(x, y, out);

  output [3:0] out;
  input [3:0] x, y;

  wire x, y, out;

  assign out = x & y;

endmodule

The Architects-ProjectStepFinal/verilog/control/control_test.v
module control_test;

/* Make a regular pulsing clock. */
reg clk = 0;
always #20 clk = !clk;

reg [3:0] x = 0;
reg [3:0] y = 0;
reg [3:0] operation = 0;
reg [3:0] Result = 0;
reg Cout = 0;
reg CinResult = 0;

initial begin
   //and
   x = 4'b1101;
   y = 4'b1110;
   operation = 4'h0;
   #10;
   x = 4'b1001;
   y = 4'b0101;
   #10;
   //nand
   x = 4'b1101;
   y = 4'b1110;
   operation = 4'h1;
   #10;
   x = 4'b1001;
   y = 4'b0101;
   #10;
   //or
   x = 4'b1101;
   y = 4'b1110;
   operation = 4'h2;
   #10;
   x = 4'b1001;
   y = 4'b0101;
   #10;
   //nor
   x = 4'b1101;
   y = 4'b1110;
   operation = 4'h3;
   #10;
   x = 4'b1001;
   y = 4'b0101;
   #10;
   //xor
   x = 4'b1101;
   y = 4'b1110;
   operation = 4'h4;
   #10;
   x = 4'b1001;
   y = 4'b0101;
   #10;
   //xnor
   x = 4'b1101;
   y = 4'b1110;
   operation = 4'h5;
   #10;
   x = 4'b1001;
   y = 4'b0101;
   #10;
   //not
   x = 4'b1101;
   y = 4'b1110;
   operation = 4'h6;
   #10;
   x = 4'b1001;
   y = 4'b0101;
   #10;
   //shift
   x = 4'b1101;
   y = 4'b1110;
   operation = 4'h7;
   #10;
   x = 4'b1001;
   y = 4'b0101;
   #10;
   //add
   x = 4'b1101;
   y = 4'b1110;
   CinResult = 1;
   operation = 4'h8;
   Cout = CoutResult;
   #10;
   x = 4'b1001;
   y = 4'b0101;
   Cout = CoutResult;
   #10;
   //sub
   x = 4'b1101;
   y = 4'b1110;
   CinResult = 1;
   operation = 4'h9;
   Cout = CoutResult;
   #10;
   x = 4'b1001;
   y = 4'b0101;
   Cout = CoutResult;
   #10;
   //mult
   x = 4'b1101;
   y = 4'b1110;
   CinResult = 1;
   operation = 4'hA;
   Cout = CoutResult;
   #10;
   x = 4'b1001;
   y = 4'b0101;
   Cout = CoutResult;
   #10;
   $finish;
end

wire [3:0] AndResult, NandResult, OrResult, NorResult, XorResult, XnorResult, NotResult, ShiftResult, AddResult, SubResult;
wire [7:0] MultResult;
wire CoutResult;

//instantiations
and_4b and4(.x(x), .y(y), .out(AndResult));
nand_4b nand4(.x(x), .y(y), .out(NandResult));
or_4b or4(.x(x), .y(y), .out(OrResult));
nor_4b nor4(.x(x), .y(y), .out(NorResult));
xor_4b xor4(.x(x), .y(y), .out(XorResult));
xnor_4b xnor4(.x(x), .y(y), .out(XnorResult));
not_4b not4(.x(x), .out(NotResult));
shift_4b shift4(.x(x), .y(y));
add_4b add4(.x(x), .y(y), .out(AddResult), .Cin(CinResult), .Cout(CoutResult));
sub_4b sub4(.x(x), .y(y), .out(SubResult), .Cin(CinResult), .Cout(CoutResult));
mult_4b mult4(.x(x), .y(y), .out(MultResult), .Cin(CinResult), .Cout(CoutResult));

//switch case
always @* begin
case (operation)
   4'h0: Result = AndResult;
   4'h1: Result = NandResult;
   4'h2: Result = OrResult;
   4'h3: Result = NorResult;
   4'h4: Result = XorResult;
   4'h5: Result = XnorResult;
   4'h6: Result = NotResult;
   4'h7: Result = ShiftResult;
   4'h8: Result = AddResult;
   4'h9: Result = SubResult;
   4'hA: Result = MultResult;
endcase
end

initial begin
   $dumpfile("control.vcd");
   $dumpvars(0,clk);
   $dumpvars(1,x);
   $dumpvars(2,y);
   $dumpvars (3, Cout);
   $dumpvars (4, CinResult);
   $dumpvars (5, Result);
end

initial
   $monitor("At time %t, x(%b) and y(%b) with CinResult(%b)= Result(%b) with Cout(%b)",
   $time, x, y, CinResult, Result, Cout);
endmodule

The Architects-ProjectStepFinal/verilog/control.vcd
$date
	Thu Nov 30 23:48:02 2023
$end
$version
	Icarus Verilog
$end
$timescale
	1s
$end
$scope module control_test $end
$var reg 1 ! clk $end
$upscope $end
$scope module control_test $end
$var reg 4 " x [3:0] $end
$upscope $end
$scope module control_test $end
$var reg 4 # y [3:0] $end
$upscope $end
$scope module control_test $end
$var reg 1 $ Cout $end
$upscope $end
$scope module control_test $end
$var reg 1 % CinResult $end
$upscope $end
$scope module control_test $end
$var reg 4 & Result [3:0] $end
$upscope $end
$enddefinitions $end
$comment Show the parameter values. $end
$dumpall
$end
#0
$dumpvars
b1100 &
0%
0$
b1110 #
b1101 "
0!
$end
#10
b1 &
b101 #
b1001 "
#20
b11 &
b1110 #
b1101 "
1!
#30
b1110 &
b101 #
b1001 "
#40
b1111 &
b1110 #
b1101 "
0!
#50
b1101 &
b101 #
b1001 "
#60
b0 &
b1110 #
b1101 "
1!
#70
b10 &
b101 #
b1001 "
#80
b11 &
b1110 #
b1101 "
0!
#90
b1100 &
b101 #
b1001 "
#100
b1100 &
b1110 #
b1101 "
1!
#110
b11 &
b101 #
b1001 "
#120
b10 &
b1110 #
b1101 "
0!
#130
b110 &
b101 #
b1001 "
#140
b1000 &
b1110 #
b1101 "
1!
#150
b100 &
b101 #
b1001 "
#160
b1100 &
1%
b1110 #
b1101 "
0!
#170
b1111 &
x$
b101 #
b1001 "
#180
b1110 &
0$
b1110 #
b1101 "
1!
#190
b11 &
x$
b101 #
b1001 "
#200
b110 &
0$
b1110 #
b1101 "
0!
#210
b1101 &
x$
b101 #
b1001 "
